sequence_detector_11010.v
/*  Máquina de estados detector de secuencia

    Autores:
    Victoria Fierro Aveytia A01247288
    Blanca Abigail Méndez Delgado A01247329

    Descripcion:
    En el siguiente codigo se realiza una maquina de estados que busca
    detectar la secuencia 11010, con una salida final de 1 
    cuando se completa la secuencia.
*/

module sequence_detector_11010(   // inicializacion de todas las variables
    input sequence_in, clk, reset,
    output reg match_sequence
);

parameter A = 3'b000,  // establecemos parametros de 3 bits para poder
          B = 3'b001,  // representar los 6 estados que necesitamos
          C = 3'b010,
          D = 3'b011,
          E = 3'b100,
          F = 3'b101;

reg [2:0] current_state, next_state;  // deben de tener la misma cantidad de bits que los parametros

always @(posedge clk or posedge reset)
begin 
    if(reset)  // valor inicial al que se regresa en caso de reset
        current_state <= A;
    else      // valor de current_state cuando no hay reset
        current_state <= next_state;
end 

always @(*)  // maquina de estados
begin
    match_sequence = 0;  // se inicializa en 0 y solo tendra un cambio cuando se complete la secuencia

    case(current_state)  // condiciones de cambio de estado

        A:   // se busca obtener 1 para seguir
        begin
            if(sequence_in == 1)
                next_state = B;  // 1
            else
                next_state = A;
        end

        B:   // se busca obtener 1 para seguir
        begin
            if(sequence_in == 1)
                next_state = C;  // 11
            else
                next_state = B;
        end

        C:    // se busca obtener 0 para seguir
        begin
           if(sequence_in == 0)
                next_state = D;  // 110
            else
                next_state = B; // se regresa a B (1)
        end

        D:    // se busca obtener 1 para seguir
        begin
            if(sequence_in == 1)
                next_state = E;  // 1101
            else
                next_state = A; // se regresa a A (0)
        end

        E:    // se busca obtener 0 para seguir
        begin
            if(sequence_in == 0)
                next_state = F;  // 11010
            else
                next_state = B; // se regresa a B (1)
        end

        F:   // se completa la secuencia y se decide a donde regresar
        begin
            if(sequence_in == 0)
            begin
                match_sequence = 1;  // salida = 1
                next_state = A;      // reinicia la secuencia en A (0)
            end
            else
                next_state = B;      // reinicia la secuencia en B (1)
        end

        default:  // estado en el que automaticamente se inicializa 
            next_state = A;
    endcase
end 

endmodule

sequence_detector_11010_tb.v
/*  Testbench máquina de estados detector de secuencia

    Autores:
    Victoria Fierro Aveytia A01247288
    Blanca Abigail Mendez Delgado A01247329

    Descripcion:
    En el siguiente codigo se realiza comprueba el funcionamiento
    de una maquina de estados, que busca detectar la secuencia 11010. 
*/

module sequence_detector_11010_tb();
    reg sequence_in, clk, reset;  // se establecen los inputs a probar como registros
    wire match_sequence;  // se establecen los outputs a probar como wire

sequence_detector_11010 DUT(     // establecemos las variable del diseño 
    .sequence_in(sequence_in),   // en el tb como: .variabletb(variable del diseño)
    .clk(clk),
    .reset(reset),
    .match_sequence(match_sequence)
);

always #5 clk = ~clk; // cuantos tiempos se utilizaran en clk = 1, y cuantos en clk = 0

initial  // se prueban posibles configuraciones de la maquina de estados
begin
    sequence_in = 0;  // inicializamos todas los inputs en 0
    clk = 0;
    reset = 0;

    #20; // probamos el reset en 20 ciclos del reloj
    reset = 1; 
    #20        
    reset = 0;

    #10; // se le dan 10 ciclos de reloj a cada prueba
    sequence_in = 1;  // se utiliza la secuencia de prueba sugerida
    #10;
    sequence_in = 1;
    #10;
    sequence_in = 0;
    #10;
    sequence_in = 1;
    #10;
    sequence_in = 1;
    #10;
    sequence_in = 1;
    #10;
    sequence_in = 0;
    #10;
    sequence_in = 1;
    #10;
    sequence_in = 0;
    #10;
    sequence_in = 1;
    #10;
    sequence_in = 1;
    #10;
    sequence_in = 0;
    #10;
    sequence_in = 1;
    $finish;
end

initial
begin
    $monitor("Cambios en estado o señales");
    $monitor("Entrada = %d, Salida = %d", sequence_in, match_sequence);
end

initial
begin
    $dumpfile("sequence_detector_11010.vcd");  // genera un archivo para las señales analizadas
    $dumpvars(0,sequence_detector_11010_tb);  // establece en que tiempo empieza la simulación, y las variables a utilizar
end

endmodule

sequence_detector_11010.vcd
$date
	Sat Jun 13 11:37:25 2026
$end
$version
	Icarus Verilog
$end
$timescale
	1s
$end
$scope module sequence_detector_11010_tb $end
$var wire 1 ! match_sequence $end
$var reg 1 " clk $end
$var reg 1 # reset $end
$var reg 1 $ sequence_in $end
$scope module DUT $end
$var wire 1 " clk $end
$var wire 1 # reset $end
$var wire 1 $ sequence_in $end
$var parameter 3 % A $end
$var parameter 3 & B $end
$var parameter 3 ' C $end
$var parameter 3 ( D $end
$var parameter 3 ) E $end
$var parameter 3 * F $end
$var reg 3 + current_state [2:0] $end
$var reg 1 ! match_sequence $end
$var reg 3 , next_state [2:0] $end
$upscope $end
$upscope $end
$enddefinitions $end
$comment Show the parameter values. $end
$dumpall
b101 *
b100 )
b11 (
b10 '
b1 &
b0 %
$end
#0
$dumpvars
b0 ,
bx +
0$
0#
0"
0!
$end
#5
b0 +
1"
#10
0"
#15
1"
#20
0"
1#
#25
1"
#30
0"
#35
1"
#40
0"
0#
#45
1"
#50
b1 ,
0"
1$
#55
b10 ,
b1 +
1"
#60
0"
#65
b1 ,
b10 +
1"
#70
b11 ,
0"
0$
#75
b0 ,
b11 +
1"
#80
b100 ,
0"
1$
#85
b1 ,
b100 +
1"
#90
0"
#95
b10 ,
b1 +
1"
#100
0"
#105
b1 ,
b10 +
1"
#110
b11 ,
0"
0$
#115
b0 ,
b11 +
1"
#120
b100 ,
0"
1$
#125
b1 ,
b100 +
1"
#130
b101 ,
0"
0$
#135
b0 ,
1!
b101 +
1"
#140
b1 ,
0!
0"
1$
#145
b10 ,
b1 +
1"
#150
0"
#155
b1 ,
b10 +
1"
#160
b11 ,
0"
0$
#165
b0 ,
b11 +
1"
#170
b100 ,
0"
1$
